Metadata-Version: 2.1
Name: Funciones-experimental
Version: 0.0.1
Summary: Librería para leer ficheros PDFs y extraer la información en formato str
Home-page: https://github.com/LuacesManuel
Author: Los pibes del grupo 7
Author-email: manueluaces00@gmail.com
License: MIT
